yamlmod.py
yamlmod-0.0.1.dist-info/DESCRIPTION.rst
yamlmod-0.0.1.dist-info/metadata.json
yamlmod-0.0.1.dist-info/WHEEL
yamlmod-0.0.1.dist-info/top_level.txt
yamlmod-0.0.1.dist-info/METADATA
yamlmod-0.0.1.dist-info/RECORD
