Metadata-Version: 2.0
Name: yamlmod
Version: 0.0.1
Summary: UNKNOWN
Home-page: https://github.com/sciyoshi/yamlmod/
Author: Samuel Cormier-Iijima
Author-email: sciyoshi@gmail.com
License: MIT
Keywords: yaml module imports hooks importhook
Platform: UNKNOWN
Classifier: Development Status :: 3 - Alpha
Classifier: Intended Audience :: Developers
Classifier: License :: OSI Approved :: MIT License
Classifier: Programming Language :: Python :: 2
Classifier: Programming Language :: Python :: 2.6
Classifier: Programming Language :: Python :: 2.7
Classifier: Programming Language :: Python :: 3
Classifier: Programming Language :: Python :: 3.3
Classifier: Programming Language :: Python :: 3.4
Requires-Dist: pyyaml (>=3.0)
